pythonimmediate/__init__.py
pythonimmediate/communicate.py
pythonimmediate/copy_to_stderr.py
pythonimmediate/decode_8bit.py
pythonimmediate/engine.py
pythonimmediate/pytotex.py
pythonimmediate/simple.py
pythonimmediate/textopy.py
pythonimmediate_tex-0.1.0.dist-info/METADATA
pythonimmediate_tex-0.1.0.dist-info/WHEEL
pythonimmediate_tex-0.1.0.dist-info/top_level.txt
pythonimmediate_tex-0.1.0.dist-info/RECORD
