Metadata-Version: 2.1
Name: pythonimmediate-tex
Version: 0.1.0
Summary: Python helper for TeX library to run Python code
Home-page: https://github.com/user202729/TeXlib
Author: user202729
License: LPPL 1.3c
Classifier: License :: OSI Approved
Classifier: Operating System :: OS Independent
Classifier: Programming Language :: Python :: 3
Classifier: Topic :: Text Processing :: Markup :: LaTeX
